sun_idea/__init__.py
sun_idea/sun_config/__init__.py
sun_idea/sun_config/sun_idea_config.py
sun_idea/sun_module/__init__.py
sun_idea/sun_module/multi_task.py
sun_idea/sun_utils/__init__.py
samidea-0.0.7.dist-info/METADATA
samidea-0.0.7.dist-info/WHEEL
samidea-0.0.7.dist-info/licenses/LICENSE
samidea-0.0.7.dist-info/RECORD
