Metadata-Version: 2.1
Name: SamIdea
Version: 0.0.7
Summary: sun_idea is a package for multiprocess
Project-URL: Homepage, https://github.com/sunxiaowu?tab=projects
Author-email: 孙小五 <sunshuanglongdf@gmail.com>
License: MIT License
License-File: LICENSE
Classifier: License :: OSI Approved :: MIT License
Classifier: Operating System :: OS Independent
Classifier: Programming Language :: Python :: 3
Requires-Python: >=3.8
Requires-Dist: tqdm>=4.64.0
